setup.py
pytest_pass/__init__.py
pytest_pass/pytest_pass.py
pytest_pass.egg-info/PKG-INFO
pytest_pass.egg-info/SOURCES.txt
pytest_pass.egg-info/dependency_links.txt
pytest_pass.egg-info/top_level.txt