Metadata-Version: 1.0
Name: pytest-pass
Version: 1.1
Summary: Check out https://github.com/elilutsky/pytest-pass
Home-page: UNKNOWN
Author: elil
Author-email: eli3143@gmail.com
License: UNKNOWN
Platform: UNKNOWN
